{
  "project_info": {
    "project_number": "545126409370",
    "project_id": "quizmaker-160b0",
    "storage_bucket": "quizmaker-160b0.appspot.com"
  },
  "client": [
    {
      "client_info": {
        "mobilesdk_app_id": "1:545126409370:android:df07bf33a00c8acfe3eb23",
        "android_client_info": {
          "package_name": "com.example.authentification"
        }
      },
      "oauth_client": [
        {
          "client_id": "545126409370-s405s7nmbu5gmjfkac7v6b94sj9jl7ll.apps.googleusercontent.com",
          "client_type": 3
        }
      ],
      "api_key": [
        {
          "current_key": "AIzaSyDGgKelzKfuqjME3u4K6KU3W64Nt1Pu4wA"
        }
      ],
      "services": {
        "appinvite_service": {
          "other_platform_oauth_client": [
            {
              "client_id": "545126409370-s405s7nmbu5gmjfkac7v6b94sj9jl7ll.apps.googleusercontent.com",
              "client_type": 3
            }
          ]
        }
      }
    },
    {
      "client_info": {
        "mobilesdk_app_id": "1:545126409370:android:302da4041aebc1b0e3eb23",
        "android_client_info": {
          "package_name": "com.example.quizapp2"
        }
      },
      "oauth_client": [
        {
          "client_id": "545126409370-s405s7nmbu5gmjfkac7v6b94sj9jl7ll.apps.googleusercontent.com",
          "client_type": 3
        }
      ],
      "api_key": [
        {
          "current_key": "AIzaSyDGgKelzKfuqjME3u4K6KU3W64Nt1Pu4wA"
        }
      ],
      "services": {
        "appinvite_service": {
          "other_platform_oauth_client": [
            {
              "client_id": "545126409370-s405s7nmbu5gmjfkac7v6b94sj9jl7ll.apps.googleusercontent.com",
              "client_type": 3
            }
          ]
        }
      }
    },
    {
      "client_info": {
        "mobilesdk_app_id": "1:545126409370:android:e487545d384fc24fe3eb23",
        "android_client_info": {
          "package_name": "com.example.quizmakerapp"
        }
      },
      "oauth_client": [
        {
          "client_id": "545126409370-s405s7nmbu5gmjfkac7v6b94sj9jl7ll.apps.googleusercontent.com",
          "client_type": 3
        }
      ],
      "api_key": [
        {
          "current_key": "AIzaSyDGgKelzKfuqjME3u4K6KU3W64Nt1Pu4wA"
        }
      ],
      "services": {
        "appinvite_service": {
          "other_platform_oauth_client": [
            {
              "client_id": "545126409370-s405s7nmbu5gmjfkac7v6b94sj9jl7ll.apps.googleusercontent.com",
              "client_type": 3
            }
          ]
        }
      }
    }
  ],
  "configuration_version": "1"
}